MANIFEST.in
setup.py
doc/CHANGELOG.rst
doc/api.rst
doc/conf.py
doc/design.rst
doc/distribution.rst
doc/extending.rst
doc/external.rst
doc/index.rst
doc/install.rst
doc/license.rst
doc/manual.rst
doc/new-plan-2011-nov.rst
doc/overview.dia
doc/overview.png
doc/research.rst
doc/spec.rst
doc/usecases.rst
doc/_static/.place-holder
doc/_templates/.place-holder
dpm/__init__.py
dpm/config.py
dpm/db.py
dpm/download.py
dpm/lib.py
dpm/metadata.py
dpm/package.py
dpm/repository.py
dpm/spec.py
dpm/upload.py
dpm/util.py
dpm.egg-info/PKG-INFO
dpm.egg-info/SOURCES.txt
dpm.egg-info/dependency_links.txt
dpm.egg-info/entry_points.txt
dpm.egg-info/not-zip-safe
dpm.egg-info/requires.txt
dpm.egg-info/top_level.txt
dpm/cli/__init__.py
dpm/cli/base.py
dpm/cli/download.py
dpm/cli/push.py
dpm/cli/standard.py
dpm/cli/upload.py
dpm/distribution/__init__.py
dpm/distribution/base.py
dpm/distribution/jsondist.py
dpm/index/__init__.py
dpm/index/base.py
dpm/index/ckan.py
dpm/tests/__init__.py
dpm/tests/base.py
dpm/tests/test_cli.py
dpm/tests/test_config.py
dpm/tests/test_distribution.py
dpm/tests/test_download.py
dpm/tests/test_lib.py
dpm/tests/test_lib_internet.py
dpm/tests/test_metadata.py
dpm/tests/test_misc.py
dpm/tests/test_package.py
dpm/tests/test_repository.py
dpm/tests/test_setuppy.py
dpm/tests/test_spec.py
dpm/tests/test_upload.py
dpm/tests/test_util.py
dpm/tests/index/__init__.py
dpm/tests/index/test_base.py
dpm/tests/index/test_ckan.py