Metadata-Version: 1.0
Name: dpm
Version: 0.10
Summary: dpm (data package): data packaging system and utilities
Home-page: http://okfn.org/projects/dpm
Author: Open Knowledge Foundation
Author-email: info@okfn.org
License: MIT
Keywords: data,packaging,component,tool
Platform: UNKNOWN
